[
    {
        "Command": "in rage b+1+2 in rage WS+b+1+2 in rage DES b+1+2",
        "Hit level": "h x 6, (DES)",
        "Damage": "55",
        "Start up frame": "13(~43?) pc8~",
        "Block frame": "+1",
        "Hit frame": "KND",
        "Counter hit frame": "KND",
        "Notes": "Rage art"
    },
    {
        "Command": "in rage f+2+3",
        "Hit level": "m (TJ)m",
        "Damage": "12,25",
        "Start up frame": "16~17 ,36~37",
        "Block frame": "0~+1",
        "Hit frame": "SPD",
        "Counter hit frame": "SPD",
        "Notes": "Rage art, Tail spin"
    },
    {
        "Command": "in rage f+2+3, 3+4",
        "Hit level": "m (TJ)m, (SBT)",
        "Damage": "12,25",
        "Start up frame": "16~17 ,36~37",
        "Block frame": "+5~+6",
        "Hit frame": "SPD",
        "Counter hit frame": "SPD",
        "Notes": "Rage art, Tail spin"
    },
    {
        "Command": "in rage f+2+3, f+3+4",
        "Hit level": "m (TJ)m, (DBT)",
        "Damage": "12,25",
        "Start up frame": "16~17 ,36~37",
        "Block frame": "+5~+6",
        "Hit frame": "SPD",
        "Counter hit frame": "SPD",
        "Notes": "Rage art, Tail spin"
    },
    {
        "Command": "1",
        "Hit level": "h",
        "Damage": "7",
        "Start up frame": "10",
        "Block frame": "+1",
        "Hit frame": "+8",
        "Counter hit frame": "+8",
        "Notes": "-"
    },
    {
        "Command": "1, 1",
        "Hit level": "h, h",
        "Damage": "7,18",
        "Start up frame": "10",
        "Block frame": "-3",
        "Hit frame": "+5",
        "Counter hit frame": "KND",
        "Notes": "-"
    },
    {
        "Command": "1, 1, 1+2",
        "Hit level": "h, h, (DES)",
        "Damage": "7,18",
        "Start up frame": "10",
        "Block frame": "-3",
        "Hit frame": "+5",
        "Counter hit frame": "KND",
        "Notes": "-"
    },
    {
        "Command": "1, 2",
        "Hit level": "h, h",
        "Damage": "7,10",
        "Start up frame": "10",
        "Block frame": "-2",
        "Hit frame": "+4",
        "Counter hit frame": "+9",
        "Notes": "-"
    },
    {
        "Command": "1, 2, 2",
        "Hit level": "h, h, l",
        "Damage": "7,10,17",
        "Start up frame": "10",
        "Block frame": "-11~-10",
        "Hit frame": "+2~+3",
        "Counter hit frame": "KND",
        "Notes": "-"
    },
    {
        "Command": "1, 2, 2*",
        "Hit level": "h, h, l",
        "Damage": "7,10,22",
        "Start up frame": "10",
        "Block frame": "-10~-9",
        "Hit frame": "KND",
        "Counter hit frame": "KND",
        "Notes": "-"
    },
    {
        "Command": "1, 2, 4",
        "Hit level": "h, h, h",
        "Damage": "7,10,21",
        "Start up frame": "10",
        "Block frame": "-5~-4",
        "Hit frame": "KND",
        "Counter hit frame": "KND",
        "Notes": "Tail spin"
    },
    {
        "Command": "2",
        "Hit level": "h",
        "Damage": "10",
        "Start up frame": "12",
        "Block frame": "-6",
        "Hit frame": "+5",
        "Counter hit frame": "+5",
        "Notes": "-"
    },
    {
        "Command": "2, 3",
        "Hit level": "h, m",
        "Damage": "10,8",
        "Start up frame": "12",
        "Block frame": "-10~-9",
        "Hit frame": "+1~+2",
        "Counter hit frame": "+1~+2",
        "Notes": "-"
    },
    {
        "Command": "2, 3, 3",
        "Hit level": "h, m, m (TJ)",
        "Damage": "10,8,25",
        "Start up frame": "12a",
        "Block frame": "-11~-9",
        "Hit frame": "KND",
        "Counter hit frame": "KND",
        "Notes": "Tail spin"
    },
    {
        "Command": "2, 3, 4",
        "Hit level": "h, m, l (TJ)",
        "Damage": "10,7,20",
        "Start up frame": "js24~",
        "Block frame": "-13~-12",
        "Hit frame": "KND",
        "Counter hit frame": "KND",
        "Notes": "-"
    },
    {
        "Command": "2, 4",
        "Hit level": "h, h",
        "Damage": "10,21",
        "Start up frame": "12",
        "Block frame": "-5~-4",
        "Hit frame": "KND",
        "Counter hit frame": "KND",
        "Notes": "Tail spin"
    },
    {
        "Command": "3",
        "Hit level": "m",
        "Damage": "12",
        "Start up frame": "13~14",
        "Block frame": "-12~-11",
        "Hit frame": "-1~0",
        "Counter hit frame": "-1~0",
        "Notes": "-"
    },
    {
        "Command": "3, 2",
        "Hit level": "m, m x 5, (DES)",
        "Damage": "12,4*5",
        "Start up frame": "13~14",
        "Block frame": "-12",
        "Hit frame": "+5",
        "Counter hit frame": "+5",
        "Notes": "-"
    },
    {
        "Command": "4",
        "Hit level": "h",
        "Damage": "24",
        "Start up frame": "13~14",
        "Block frame": "-5~-4",
        "Hit frame": "KND",
        "Counter hit frame": "KND",
        "Notes": "Tail spin, Homing"
    },
    {
        "Command": "1+2",
        "Hit level": "m (TJ)",
        "Damage": "21",
        "Start up frame": "33~34 js7~",
        "Block frame": "-5~-4",
        "Hit frame": "KND",
        "Counter hit frame": "KND",
        "Notes": "-"
    },
    {
        "Command": "f+2",
        "Hit level": "m",
        "Damage": "12",
        "Start up frame": "17~18",
        "Block frame": "-4~-3",
        "Hit frame": "+7~+8",
        "Counter hit frame": "+7~+8",
        "Notes": "-"
    },
    {
        "Command": "f+2, 1",
        "Hit level": "m, m, (DES)",
        "Damage": "12,20",
        "Start up frame": "17~18",
        "Block frame": "-14",
        "Hit frame": "CS",
        "Counter hit frame": "CS",
        "Notes": "-"
    },
    {
        "Command": "f+2, 1+2",
        "Hit level": "m, (DES)",
        "Damage": "12",
        "Start up frame": "17~18",
        "Block frame": "-4~-3",
        "Hit frame": "+7~+8",
        "Counter hit frame": "+7~+8",
        "Notes": "-"
    },
    {
        "Command": "f+2, 3",
        "Hit level": "m, h (TJ)",
        "Damage": "12,8",
        "Start up frame": "js17~",
        "Block frame": "-8",
        "Hit frame": "+4",
        "Counter hit frame": "+4",
        "Notes": "-"
    },
    {
        "Command": "f+2, 3, f",
        "Hit level": "m, h (TJ), (Special)",
        "Damage": "12,8",
        "Start up frame": "17~a",
        "Block frame": "-12",
        "Hit frame": "0",
        "Counter hit frame": "0",
        "Notes": "-"
    },
    {
        "Command": "f+2, 3, 3",
        "Hit level": "m, h (TJ), m",
        "Damage": "12,8,22",
        "Start up frame": "js1~12",
        "Block frame": "-10~-9",
        "Hit frame": "ED",
        "Counter hit frame": "ED",
        "Notes": "wb!"
    },
    {
        "Command": "f+3",
        "Hit level": "h",
        "Damage": "10",
        "Start up frame": "14~15",
        "Block frame": "-14~-13",
        "Hit frame": "-3~-2",
        "Counter hit frame": "-3~-2",
        "Notes": "-"
    },
    {
        "Command": "f+3, 2",
        "Hit level": "h, h, (DES)",
        "Damage": "10,17",
        "Start up frame": "14~15",
        "Block frame": "-4~-2",
        "Hit frame": "KND",
        "Counter hit frame": "KND",
        "Notes": "Tail spin"
    },
    {
        "Command": "f+3, 1+2",
        "Hit level": "h, m, (DES)",
        "Damage": "13,25",
        "Start up frame": "14~15",
        "Block frame": "-13~-12",
        "Hit frame": "+8k",
        "Counter hit frame": "+8k",
        "Notes": "Tail spin"
    },
    {
        "Command": "f+4",
        "Hit level": "m",
        "Damage": "14",
        "Start up frame": "16",
        "Block frame": "-12",
        "Hit frame": "-2",
        "Counter hit frame": "-2",
        "Notes": "Homing"
    },
    {
        "Command": "f+4, 1",
        "Hit level": "m, h",
        "Damage": "14,14",
        "Start up frame": "16",
        "Block frame": "-9~-8",
        "Hit frame": "KND",
        "Counter hit frame": "KND",
        "Notes": "-"
    },
    {
        "Command": "f+4, 1, 4",
        "Hit level": "m, h, m",
        "Damage": "14,14,24",
        "Start up frame": "16",
        "Block frame": "-14~+12 (-12)",
        "Hit frame": "KND",
        "Counter hit frame": "KND",
        "Notes": "-"
    },
    {
        "Command": "f+1+2",
        "Hit level": "m",
        "Damage": "25",
        "Start up frame": "14~15",
        "Block frame": "-12~-11",
        "Hit frame": "+7~+8",
        "Counter hit frame": "+7~+8",
        "Notes": "-"
    },
    {
        "Command": "f+1+2, 3+4",
        "Hit level": "m, (Special) (TJ)(SBT)",
        "Damage": "25",
        "Start up frame": "14~15a",
        "Block frame": "-16~-15",
        "Hit frame": "+3~+4",
        "Counter hit frame": "+3~+4",
        "Notes": "-"
    },
    {
        "Command": "f+1+2, f+3+4",
        "Hit level": "m, (Special) (TJ)(DBT)",
        "Damage": "25",
        "Start up frame": "14~15a",
        "Block frame": "-16~-15",
        "Hit frame": "+3~+4",
        "Counter hit frame": "+3~+4",
        "Notes": "-"
    },
    {
        "Command": "d/f+1",
        "Hit level": "m",
        "Damage": "10",
        "Start up frame": "13",
        "Block frame": "-6",
        "Hit frame": "+5",
        "Counter hit frame": "+8",
        "Notes": "-"
    },
    {
        "Command": "d/f+1, 1",
        "Hit level": "m, h",
        "Damage": "10,20",
        "Start up frame": "13",
        "Block frame": "+1~+2",
        "Hit frame": "+8~+9",
        "Counter hit frame": "+8~+9",
        "Notes": "-"
    },
    {
        "Command": "d/f+1, 1, 2",
        "Hit level": "m, h, h x 7, (DES)",
        "Damage": "10,20,4*7",
        "Start up frame": "13",
        "Block frame": "+6",
        "Hit frame": "+8",
        "Counter hit frame": "+8",
        "Notes": "-"
    },
    {
        "Command": "d/f+1, 4",
        "Hit level": "m, m",
        "Damage": "10,17",
        "Start up frame": "13",
        "Block frame": "-9~-8",
        "Hit frame": "+5~+6s",
        "Counter hit frame": "KND",
        "Notes": "-"
    },
    {
        "Command": "d/f+2",
        "Hit level": "m",
        "Damage": "16",
        "Start up frame": "16~17",
        "Block frame": "-9~-8",
        "Hit frame": "Launch (JG?)(+7)",
        "Counter hit frame": "Launch (JG?)",
        "Notes": "-"
    },
    {
        "Command": "d/f+3",
        "Hit level": "m",
        "Damage": "14",
        "Start up frame": "16",
        "Block frame": "-9",
        "Hit frame": "+1",
        "Counter hit frame": "+1",
        "Notes": "-"
    },
    {
        "Command": "d/f+3, 3",
        "Hit level": "m, l",
        "Damage": "14,17",
        "Start up frame": "16",
        "Block frame": "-12~-11",
        "Hit frame": "+1~+2",
        "Counter hit frame": "KND",
        "Notes": "-"
    },
    {
        "Command": "d/f+4",
        "Hit level": "m",
        "Damage": "13",
        "Start up frame": "12",
        "Block frame": "-7",
        "Hit frame": "+4",
        "Counter hit frame": "+4",
        "Notes": "-"
    },
    {
        "Command": "d/f+1+2",
        "Hit level": "m, (DES)",
        "Damage": "25",
        "Start up frame": "18",
        "Block frame": "-13",
        "Hit frame": "+8",
        "Counter hit frame": "+8",
        "Notes": "Power Crush, Tail Spin"
    },
    {
        "Command": "d+2",
        "Hit level": "m",
        "Damage": "17",
        "Start up frame": "24~26",
        "Block frame": "-14~-12",
        "Hit frame": "+2~+4s",
        "Counter hit frame": "+2~+4s",
        "Notes": "-"
    },
    {
        "Command": "d+2, 4",
        "Hit level": "m, m",
        "Damage": "17,24",
        "Start up frame": "24~26a",
        "Block frame": "-13~-10",
        "Hit frame": "KND",
        "Counter hit frame": "KND",
        "Notes": "-"
    },
    {
        "Command": "d+2, 4, 1+2",
        "Hit level": "m, m, (DES)",
        "Damage": "17,24",
        "Start up frame": "24~26a",
        "Block frame": "-13~-10",
        "Hit frame": "KND",
        "Counter hit frame": "KND",
        "Notes": "-"
    },
    {
        "Command": "d+3",
        "Hit level": "l (TJ), (Special) (TC)",
        "Damage": "17",
        "Start up frame": "23~32s js9~",
        "Block frame": "-10~-1",
        "Hit frame": "+8~+17",
        "Counter hit frame": "KND",
        "Notes": "-"
    },
    {
        "Command": "d+3 (After stance ends)",
        "Hit level": "l (TJ), (Special) (TC)",
        "Damage": "17",
        "Start up frame": "23~32s js9~",
        "Block frame": "-19~-10",
        "Hit frame": "-1~+8",
        "Counter hit frame": "KND",
        "Notes": "-"
    },
    {
        "Command": "d+4",
        "Hit level": "l",
        "Damage": "15",
        "Start up frame": "17~18",
        "Block frame": "-16~-15",
        "Hit frame": "-5~-4",
        "Counter hit frame": "-5~-4",
        "Notes": "-"
    },
    {
        "Command": "d+4, 1+2",
        "Hit level": "l, h",
        "Damage": "15,20",
        "Start up frame": "17~18",
        "Block frame": "+2",
        "Hit frame": "KND",
        "Counter hit frame": "KND",
        "Notes": "Tail spin"
    },
    {
        "Command": "d+3+4",
        "Hit level": "l (TJ)",
        "Damage": "20",
        "Start up frame": "27~28 js5~ cs20~",
        "Block frame": "-37",
        "Hit frame": "KND",
        "Counter hit frame": "KND",
        "Notes": "Homing"
    },
    {
        "Command": "d+3+4, 1+2",
        "Hit level": "l (TJ), (DES)",
        "Damage": "20",
        "Start up frame": "27~28 js5~ cs20~",
        "Block frame": "-",
        "Hit frame": "KND",
        "Counter hit frame": "KND",
        "Notes": "Homing"
    },
    {
        "Command": "d/b+2",
        "Hit level": "m",
        "Damage": "17",
        "Start up frame": "18~19",
        "Block frame": "-18~-17",
        "Hit frame": "-5~-4",
        "Counter hit frame": "-5~-4",
        "Notes": "-"
    },
    {
        "Command": "d/b+2, 2",
        "Hit level": "m, m",
        "Damage": "17,13",
        "Start up frame": "18~19",
        "Block frame": "-10~-9",
        "Hit frame": "+14~+15 (SH)",
        "Counter hit frame": "+14~+15 (SH)",
        "Notes": "-"
    },
    {
        "Command": "d/b+2, 2, 1+2",
        "Hit level": "m, m, (DES)",
        "Damage": "17,13",
        "Start up frame": "18~19",
        "Block frame": "-10~-9",
        "Hit frame": "+14~+15 (SH)",
        "Counter hit frame": "+14~+15 (SH)",
        "Notes": "-"
    },
    {
        "Command": "d/b+3",
        "Hit level": "l (TC)",
        "Damage": "11",
        "Start up frame": "16s cs4~",
        "Block frame": "-12",
        "Hit frame": "-1",
        "Counter hit frame": "+4",
        "Notes": "-"
    },
    {
        "Command": "d/b+4",
        "Hit level": "l (TC)",
        "Damage": "23",
        "Start up frame": "24~25a cs6~",
        "Block frame": "-17~-16",
        "Hit frame": "KND",
        "Counter hit frame": "KND",
        "Notes": "-"
    },
    {
        "Command": "b+1",
        "Hit level": "m",
        "Damage": "15",
        "Start up frame": "15~16s",
        "Block frame": "-5~-4",
        "Hit frame": "+8~+9",
        "Counter hit frame": "+8~+9",
        "Notes": "-"
    },
    {
        "Command": "b+1, 1+2",
        "Hit level": "m, Sm, m",
        "Damage": "15,1,30",
        "Start up frame": "15~16",
        "Block frame": "-16~-14",
        "Hit frame": "Launch",
        "Counter hit frame": "Launch",
        "Notes": "-"
    },
    {
        "Command": "b+2",
        "Hit level": "m",
        "Damage": "12",
        "Start up frame": "18",
        "Block frame": "-12",
        "Hit frame": "-2",
        "Counter hit frame": "-2",
        "Notes": "-"
    },
    {
        "Command": "b+2, 1",
        "Hit level": "m, m",
        "Damage": "12,17",
        "Start up frame": "18",
        "Block frame": "-13~-12",
        "Hit frame": "+3~+4s",
        "Counter hit frame": "KND",
        "Notes": "-"
    },
    {
        "Command": "b+2, 4",
        "Hit level": "m, h",
        "Damage": "12,20",
        "Start up frame": "18",
        "Block frame": "-7~-6",
        "Hit frame": "KND",
        "Counter hit frame": "KND",
        "Notes": "Tail spin"
    },
    {
        "Command": "b+3",
        "Hit level": "m",
        "Damage": "26",
        "Start up frame": "20~22",
        "Block frame": "-8~-6",
        "Hit frame": "ED",
        "Counter hit frame": "ED",
        "Notes": "Homing"
    },
    {
        "Command": "b+4",
        "Hit level": "m",
        "Damage": "17",
        "Start up frame": "15~16",
        "Block frame": "-13~-12",
        "Hit frame": "-4~-3",
        "Counter hit frame": "CS",
        "Notes": "-"
    },
    {
        "Command": "b+4, 3",
        "Hit level": "m, m",
        "Damage": "17,20",
        "Start up frame": "js1~27",
        "Block frame": "-11~-10",
        "Hit frame": "+6~+7s",
        "Counter hit frame": "KND",
        "Notes": "-"
    },
    {
        "Command": "b+4, 3, 1+2",
        "Hit level": "m (TJ), m, (DES)",
        "Damage": "17,15",
        "Start up frame": "1~27",
        "Block frame": "-11~-10",
        "Hit frame": "+6~+7s",
        "Counter hit frame": "KND",
        "Notes": "-"
    },
    {
        "Command": "b+4, 4",
        "Hit level": "m, m",
        "Damage": "17,17",
        "Start up frame": "js1~27",
        "Block frame": "-37",
        "Hit frame": "Launch",
        "Counter hit frame": "Launch",
        "Notes": "-"
    },
    {
        "Command": "b+4, 4, 3+4/td>",
        "Hit level": "m, m, (SBT)",
        "Damage": "17,17",
        "Start up frame": "15~16",
        "Block frame": "-19",
        "Hit frame": "Launch",
        "Counter hit frame": "Launch",
        "Notes": "-"
    },
    {
        "Command": "b+4, 4, f+3+4/td>",
        "Hit level": "m, m (DBT)",
        "Damage": "17,17",
        "Start up frame": "15~16",
        "Block frame": "-19",
        "Hit frame": "Launch",
        "Counter hit frame": "Launch",
        "Notes": "-"
    },
    {
        "Command": "b+3+4",
        "Hit level": "m (TJ)",
        "Damage": "20",
        "Start up frame": "19~20 js6~",
        "Block frame": "-17~-16",
        "Hit frame": "Launch",
        "Counter hit frame": "Launch",
        "Notes": "-"
    },
    {
        "Command": "b+3+4, 3+4",
        "Hit level": "m (TJ), m (TJ)",
        "Damage": "20,35",
        "Start up frame": "js1~",
        "Block frame": "+5~+10s",
        "Hit frame": "KND",
        "Counter hit frame": "KND",
        "Notes": "-"
    },
    {
        "Command": "b+2+3",
        "Hit level": "!",
        "Damage": "50",
        "Start up frame": "75",
        "Block frame": "KND",
        "Hit frame": "KND",
        "Counter hit frame": "KND",
        "Notes": "-"
    },
    {
        "Command": "u/b+3+4",
        "Hit level": "m (TJ)",
        "Damage": "25",
        "Start up frame": "37~39 js5~",
        "Block frame": "+2~+4s",
        "Hit frame": "KND",
        "Counter hit frame": "KND",
        "Notes": "-"
    },
    {
        "Command": "BT 3+4",
        "Hit level": "m (TJ)",
        "Damage": "25",
        "Start up frame": "37~39b js5~",
        "Block frame": "+2~+4s",
        "Hit frame": "KND",
        "Counter hit frame": "KND",
        "Notes": "-"
    },
    {
        "Command": "u/b+3+4, 1+2 or BT 3+4, 1+2",
        "Hit level": "m (TJ), m?",
        "Damage": "25,20",
        "Start up frame": "js1~20 ar48~",
        "Block frame": "-14~-13",
        "Hit frame": "Launch",
        "Counter hit frame": "Launch",
        "Notes": "-"
    },
    {
        "Command": "u/b or u or u/f+3",
        "Hit level": "m (TJ)",
        "Damage": "15",
        "Start up frame": "17~18 js9~",
        "Block frame": "-52~-51",
        "Hit frame": "-24~-23 (SH)",
        "Counter hit frame": "-24~-23 (SH)",
        "Notes": "-"
    },
    {
        "Command": "u/f+3, 2",
        "Hit level": "m (TJ), m (TJ)",
        "Damage": "15,30",
        "Start up frame": "js1~",
        "Block frame": "-14~-9",
        "Hit frame": "KND",
        "Counter hit frame": "KND",
        "Notes": "-"
    },
    {
        "Command": "u/f+3, 3+4",
        "Hit level": "m (TJ), (Special) (TJ)(SBT)",
        "Damage": "15",
        "Start up frame": "js1~",
        "Block frame": "-29~-28",
        "Hit frame": "-3~-2 (SH)",
        "Counter hit frame": "-3~-2 (SH)",
        "Notes": "-"
    },
    {
        "Command": "u/f+3, f+3+4",
        "Hit level": "m (TJ), (Special) (TJ)(DBT)",
        "Damage": "15",
        "Start up frame": "js1~",
        "Block frame": "-29~-28",
        "Hit frame": "-3~-2 (SH)",
        "Counter hit frame": "-3~-2 (SH)",
        "Notes": "-"
    },
    {
        "Command": "u or u/f+4",
        "Hit level": "m (TJ)",
        "Damage": "10",
        "Start up frame": "15~16 js9~",
        "Block frame": "-15~-14",
        "Hit frame": "-4~-3",
        "Counter hit frame": "-4~-3",
        "Notes": "-"
    },
    {
        "Command": "u/f+4, 4",
        "Hit level": "m (TJ), m",
        "Damage": "10,10",
        "Start up frame": "js1~",
        "Block frame": "-13~-11s",
        "Hit frame": "BU",
        "Counter hit frame": "BU",
        "Notes": "-"
    },
    {
        "Command": "u or u/f+3+4",
        "Hit level": "m (TJ)",
        "Damage": "28",
        "Start up frame": "38~41 js9~",
        "Block frame": "0~+3",
        "Hit frame": "KND",
        "Counter hit frame": "KND",
        "Notes": "-"
    },
    {
        "Command": "f, F+2",
        "Hit level": "m",
        "Damage": "18",
        "Start up frame": "16~17 (17~)",
        "Block frame": "-18~-17",
        "Hit frame": "KND",
        "Counter hit frame": "KND",
        "Notes": "-"
    },
    {
        "Command": "f, F+2, 3",
        "Hit level": "m, m",
        "Damage": "18,25",
        "Start up frame": "16~17 (17~)",
        "Block frame": "-13~-11",
        "Hit frame": "KMED",
        "Counter hit frame": "KMED",
        "Notes": "-"
    },
    {
        "Command": "f, F+3",
        "Hit level": "m",
        "Damage": "12",
        "Start up frame": "18~19 (19~) js15~",
        "Block frame": "-18~-17",
        "Hit frame": "-6~-5",
        "Counter hit frame": "-6~-5",
        "Notes": "-"
    },
    {
        "Command": "f, F+3, 4",
        "Hit level": "m, h (TJ)",
        "Damage": "12,15",
        "Start up frame": "js1~",
        "Block frame": "-9~-8",
        "Hit frame": "KND",
        "Counter hit frame": "KND",
        "Notes": "-"
    },
    {
        "Command": "f, F+3, 4, 1+2",
        "Hit level": "m, h (TJ), (DES)",
        "Damage": "12,15",
        "Start up frame": "js1~",
        "Block frame": "-9~-8",
        "Hit frame": "KND",
        "Counter hit frame": "KND",
        "Notes": "-"
    },
    {
        "Command": "f, F+3, 4, 4",
        "Hit level": "m, h (TJ), m",
        "Damage": "12,15,25",
        "Start up frame": "js1~12",
        "Block frame": "-10~-8",
        "Hit frame": "KND",
        "Counter hit frame": "KND",
        "Notes": "Tail spin"
    },
    {
        "Command": "f, F+3, 4, 4, 1+2",
        "Hit level": "m, h (TJ), m, (DES)",
        "Damage": "12,15,25",
        "Start up frame": "js1~12",
        "Block frame": "-10~-8",
        "Hit frame": "KND",
        "Counter hit frame": "KND",
        "Notes": "Tail spin"
    },
    {
        "Command": "f, F+4",
        "Hit level": "m",
        "Damage": "18",
        "Start up frame": "19~26 (20~)",
        "Block frame": "-11~-4",
        "Hit frame": "Throw(+5b)",
        "Counter hit frame": "Throw(+5b)",
        "Notes": "-"
    },
    {
        "Command": "f, F+4 When hit f or b+1",
        "Hit level": "m, m",
        "Damage": "18,22",
        "Start up frame": "19~26 (20~)",
        "Block frame": "-",
        "Hit frame": "KND",
        "Counter hit frame": "-",
        "Notes": "-"
    },
    {
        "Command": "f, F+1+2",
        "Hit level": "mm",
        "Damage": "5,18",
        "Start up frame": "17~18, 30~31 (18~)",
        "Block frame": "-16~-15",
        "Hit frame": "CS",
        "Counter hit frame": "CS",
        "Notes": "-"
    },
    {
        "Command": "f, F+1+2 When hit 2",
        "Hit level": "mm, m x 6, (DES)",
        "Damage": "5,18,2*6",
        "Start up frame": "17~18, 30~31 (18~)",
        "Block frame": "-",
        "Hit frame": "CS",
        "Counter hit frame": "CS",
        "Notes": "-"
    },
    {
        "Command": "b, f+2",
        "Hit level": "h",
        "Damage": "26",
        "Start up frame": "16~24 (16~) pc8~15",
        "Block frame": "-8~0",
        "Hit frame": "KND",
        "Counter hit frame": "KND",
        "Notes": "Power crush"
    },
    {
        "Command": "b, B+1+4",
        "Hit level": "h! (TJ)",
        "Damage": "50",
        "Start up frame": "63~80 (64~)",
        "Block frame": "KND",
        "Hit frame": "KND",
        "Counter hit frame": "KND",
        "Notes": "-"
    },
    {
        "Command": "f, f, f+2",
        "Hit level": "h",
        "Damage": "30",
        "Start up frame": "13~15 (16~) js3~",
        "Block frame": "+5~+7",
        "Hit frame": "KND",
        "Counter hit frame": "KND",
        "Notes": "-"
    },
    {
        "Command": "f, f, f+3",
        "Hit level": "m (TJ)",
        "Damage": "15",
        "Start up frame": "18~19 (21~) js3~",
        "Block frame": "-4~-3",
        "Hit frame": "+6~+7",
        "Counter hit frame": "+6~+7",
        "Notes": "-"
    },
    {
        "Command": "f, f, f+3, 4",
        "Hit level": "m (TJ), m (TJ)",
        "Damage": "15,20",
        "Start up frame": "js1~",
        "Block frame": "-7~-5",
        "Hit frame": "KMED",
        "Counter hit frame": "KMED",
        "Notes": "Tail spin"
    },
    {
        "Command": "WR+1+2",
        "Hit level": "m (TJ)",
        "Damage": "24",
        "Start up frame": "18~36 js5~",
        "Block frame": "-3~+15",
        "Hit frame": "KND",
        "Counter hit frame": "KND",
        "Notes": "-"
    },
    {
        "Command": "WS+1",
        "Hit level": "m",
        "Damage": "12",
        "Start up frame": "13~14",
        "Block frame": "-12~-11",
        "Hit frame": "-1~0",
        "Counter hit frame": "-1~0",
        "Notes": "-"
    },
    {
        "Command": "WS+1, 2",
        "Hit level": "m, h",
        "Damage": "12,9",
        "Start up frame": "13~14",
        "Block frame": "-5~-4",
        "Hit frame": "+6~+7",
        "Counter hit frame": "+6~+7",
        "Notes": "-"
    },
    {
        "Command": "WS+1, 2, 3",
        "Hit level": "m, h, m",
        "Damage": "12,9,23",
        "Start up frame": "13~14",
        "Block frame": "-10~-9",
        "Hit frame": "Launch",
        "Counter hit frame": "Launch",
        "Notes": "-"
    },
    {
        "Command": "WS+1, 2, 3, 1+2",
        "Hit level": "m, h, m, (DES)",
        "Damage": "12,9,23",
        "Start up frame": "13~14",
        "Block frame": "-10~-9",
        "Hit frame": "Launch",
        "Counter hit frame": "Launch",
        "Notes": "-"
    },
    {
        "Command": "WS+2",
        "Hit level": "m",
        "Damage": "24",
        "Start up frame": "17~18",
        "Block frame": "-13~-12",
        "Hit frame": "Launch",
        "Counter hit frame": "Launch",
        "Notes": "-"
    },
    {
        "Command": "WS+2, 3+4",
        "Hit level": "m, (Special) (TJ)(SBT)",
        "Damage": "24",
        "Start up frame": "17~18 js1~",
        "Block frame": "-7~-6",
        "Hit frame": "Launch",
        "Counter hit frame": "Launch",
        "Notes": "-"
    },
    {
        "Command": "WS+2, f+3+4",
        "Hit level": "m, (Special) (TJ)(DBT)",
        "Damage": "24",
        "Start up frame": "17~18 js1~",
        "Block frame": "-7~-6",
        "Hit frame": "Launch",
        "Counter hit frame": "Launch",
        "Notes": "-"
    },
    {
        "Command": "WS+3",
        "Hit level": "m, (Special)",
        "Damage": "18",
        "Start up frame": "19~20a",
        "Block frame": "-135~-134",
        "Hit frame": "-126~-125",
        "Counter hit frame": "-126~-125",
        "Notes": "-"
    },
    {
        "Command": "WS+3, 3, B (Cancel)",
        "Hit level": "m, (Special)",
        "Damage": "18",
        "Start up frame": "19~20",
        "Block frame": "-14~-13",
        "Hit frame": "-1~0",
        "Counter hit frame": "-1~0",
        "Notes": "-"
    },
    {
        "Command": "WS+3, 3 (one spin)",
        "Hit level": "m",
        "Damage": "20",
        "Start up frame": "13~14",
        "Block frame": "-10~-9",
        "Hit frame": "+11kg",
        "Counter hit frame": "KND",
        "Notes": "Tail spin"
    },
    {
        "Command": "WS+3, 3",
        "Hit level": "m",
        "Damage": "22",
        "Start up frame": "13~14",
        "Block frame": "0~+1",
        "Hit frame": "KND",
        "Counter hit frame": "KND",
        "Notes": "Tail spin"
    },
    {
        "Command": "WS+3, d+3",
        "Hit level": "l (TC)",
        "Damage": "20",
        "Start up frame": "30~31s cs9~",
        "Block frame": "-12~-11",
        "Hit frame": "KND",
        "Counter hit frame": "KND",
        "Notes": "-"
    },
    {
        "Command": "WS+4",
        "Hit level": "m",
        "Damage": "15",
        "Start up frame": "11~12",
        "Block frame": "-5~-4",
        "Hit frame": "+6~+7",
        "Counter hit frame": "+6~+7",
        "Notes": "-"
    },
    {
        "Command": "WS+1+2",
        "Hit level": "m",
        "Damage": "20",
        "Start up frame": "20~21s",
        "Block frame": "-8~-7",
        "Hit frame": "KND",
        "Counter hit frame": "KND",
        "Notes": "Homing"
    },
    {
        "Command": "WS+1+2, * (two spins)",
        "Hit level": "m",
        "Damage": "24",
        "Start up frame": "28~29s",
        "Block frame": "-4~-3",
        "Hit frame": "KND",
        "Counter hit frame": "KND",
        "Notes": "Homing"
    },
    {
        "Command": "WS+1+2, * (three spins)",
        "Hit level": "m",
        "Damage": "28",
        "Start up frame": "39~40s",
        "Block frame": "0~+1",
        "Hit frame": "AZUD",
        "Counter hit frame": "AZUD",
        "Notes": "Homing"
    },
    {
        "Command": "FC+d/f+1+2",
        "Hit level": "ll",
        "Damage": "10,16",
        "Start up frame": "21~23, 31~33 cs1~",
        "Block frame": "-11~-9",
        "Hit frame": "+5~+7s",
        "Counter hit frame": "+5~+7s",
        "Notes": "-"
    },
    {
        "Command": "FC+d/f+1+2 , 1+2",
        "Hit level": "ll, (DES)",
        "Damage": "10,16",
        "Start up frame": "21~23, 31~33 cs1~",
        "Block frame": "-11~-9",
        "Hit frame": "+5~+7s",
        "Counter hit frame": "+5~+7s",
        "Notes": "-"
    },
    {
        "Command": "SS+4",
        "Hit level": "l",
        "Damage": "15",
        "Start up frame": "24~25 (33~) cs6~",
        "Block frame": "-12~-11",
        "Hit frame": "+2",
        "Counter hit frame": "+7~+8",
        "Notes": "-"
    },
    {
        "Command": "SS+4 , 1+2",
        "Hit level": "l, h x 3 (TJ), m (TJ)",
        "Damage": "15,5*4",
        "Start up frame": "js15~",
        "Block frame": "-10~-9",
        "Hit frame": "+8~+9",
        "Counter hit frame": "+8~+9",
        "Notes": "-"
    },
    {
        "Command": "BT 4",
        "Hit level": "m (TJ)",
        "Damage": "20",
        "Start up frame": "16~17b",
        "Block frame": "-3~-2",
        "Hit frame": "KND",
        "Counter hit frame": "KND",
        "Notes": "-"
    },
    {
        "Command": "Opponent Down d/b+1+2",
        "Hit level": "l(On grounded opponent)",
        "Damage": "20",
        "Start up frame": "24~26",
        "Block frame": "-14",
        "Hit frame": "KND",
        "Counter hit frame": "KND",
        "Notes": "-"
    },
    {
        "Command": "Grounded face up 1+2",
        "Hit level": "(Special) (TJ)",
        "Damage": "-",
        "Start up frame": "a",
        "Block frame": "-",
        "Hit frame": "-",
        "Counter hit frame": "-",
        "Notes": "-"
    },
    {
        "Command": "Grounded face up 1+2, 3+4",
        "Hit level": "(Special) (TJ), m (TJ)",
        "Damage": "35",
        "Start up frame": "22~23 (42~43) js1~",
        "Block frame": "-10~-9",
        "Hit frame": "KND",
        "Counter hit frame": "KND",
        "Notes": "-"
    },
    {
        "Command": "1+2+3",
        "Hit level": "(Special) (TJ)",
        "Damage": "-",
        "Start up frame": "a",
        "Block frame": "-",
        "Hit frame": "-",
        "Counter hit frame": "-",
        "Notes": "-"
    },
    {
        "Command": "1+2+4",
        "Hit level": "(Special)",
        "Damage": "-",
        "Start up frame": "(g)",
        "Block frame": "-",
        "Hit frame": "-",
        "Counter hit frame": "-",
        "Notes": "-"
    },
    {
        "Command": "1+2+3+4",
        "Hit level": "(Special) (TJ)",
        "Damage": "-",
        "Start up frame": "a",
        "Block frame": "-",
        "Hit frame": "-",
        "Counter hit frame": "-",
        "Notes": "-"
    },
    {
        "Command": "1+2+3+4, 1+2",
        "Hit level": "(Special) (TJ), (DES)",
        "Damage": "-",
        "Start up frame": "a",
        "Block frame": "-",
        "Hit frame": "-",
        "Counter hit frame": "-",
        "Notes": "-"
    },
    {
        "Command": "d/b+1",
        "Hit level": "(Special) (TC)",
        "Damage": "-",
        "Start up frame": "s(cs4) 15~",
        "Block frame": "-",
        "Hit frame": "-",
        "Counter hit frame": "-",
        "Notes": "-"
    },
    {
        "Command": "d/b+1~1",
        "Hit level": "h",
        "Damage": "31",
        "Start up frame": "11~13 (26~) cs4~15",
        "Block frame": "+4~+6",
        "Hit frame": "KMED",
        "Counter hit frame": "KMED",
        "Notes": "Tail spin"
    },
    {
        "Command": "d/b+1~2",
        "Hit level": "h! (Sky)",
        "Damage": "20(,3)",
        "Start up frame": "34~75(49~)",
        "Block frame": "KND",
        "Hit frame": "KND",
        "Counter hit frame": "KND",
        "Notes": "-"
    },
    {
        "Command": "d/b+1~3",
        "Hit level": "m (TJ)",
        "Damage": "30",
        "Start up frame": "24~27 (39~) js15~",
        "Block frame": "-9",
        "Hit frame": "KND",
        "Counter hit frame": "KND",
        "Notes": "-"
    },
    {
        "Command": "d/b+1~4",
        "Hit level": "m",
        "Damage": "30",
        "Start up frame": "18~23 (33~) js17~",
        "Block frame": "-9~-4",
        "Hit frame": "Launch",
        "Counter hit frame": "Launch",
        "Notes": "-"
    },
    {
        "Command": "f+3+4 (to SBT)",
        "Hit level": "(Special) (TJ)(SBT)",
        "Damage": "-",
        "Start up frame": "18~23 (33~) 17~",
        "Block frame": "-",
        "Hit frame": "-",
        "Counter hit frame": "-",
        "Notes": "-"
    },
    {
        "Command": "f+3+4, B",
        "Hit level": "(Special)",
        "Damage": "-",
        "Start up frame": "s(47~)",
        "Block frame": "-",
        "Hit frame": "-",
        "Counter hit frame": "-",
        "Notes": "-"
    },
    {
        "Command": "f+3+4, D",
        "Hit level": "(Special)",
        "Damage": "-",
        "Start up frame": "s(36~)",
        "Block frame": "-",
        "Hit frame": "-",
        "Counter hit frame": "-",
        "Notes": "-"
    },
    {
        "Command": "SBT 1",
        "Hit level": "m",
        "Damage": "12",
        "Start up frame": "13~14 (38~) js1~",
        "Block frame": "-15~-14",
        "Hit frame": "0~+1",
        "Counter hit frame": "0~+1",
        "Notes": "-"
    },
    {
        "Command": "SBT 1, 2",
        "Hit level": "m, m",
        "Damage": "12,13",
        "Start up frame": "js1~",
        "Block frame": "-9~-8",
        "Hit frame": "+2~+3",
        "Counter hit frame": "+7~+8s",
        "Notes": "-"
    },
    {
        "Command": "SBT 1, 2, 1",
        "Hit level": "m, m, m",
        "Damage": "12,13,7",
        "Start up frame": "js1~",
        "Block frame": "-20~-19",
        "Hit frame": "-12~-11",
        "Counter hit frame": "-12~-11",
        "Notes": "-"
    },
    {
        "Command": "SBT 1, 2, 1, 3+4",
        "Hit level": "m, m, m, mm",
        "Damage": "12,13,10,10,30",
        "Start up frame": "js1~",
        "Block frame": "-18",
        "Hit frame": "KND",
        "Counter hit frame": "KND",
        "Notes": "-"
    },
    {
        "Command": "SBT 1, 2, 1 , 3+4, 1+2",
        "Hit level": "m, m, m, mm, (DES)",
        "Damage": "12,13,7,5,28",
        "Start up frame": "js1~",
        "Block frame": "-18~-17",
        "Hit frame": "KND",
        "Counter hit frame": "KND",
        "Notes": "-"
    },
    {
        "Command": "SBT 2",
        "Hit level": "m",
        "Damage": "25",
        "Start up frame": "16~27 (41~) js1~",
        "Block frame": "-8~+3",
        "Hit frame": "KND",
        "Counter hit frame": "KND",
        "Notes": "-"
    },
    {
        "Command": "SBT 2, 1+2",
        "Hit level": "m, (DES)",
        "Damage": "25",
        "Start up frame": "16~27 (41~) js1~",
        "Block frame": "-8~+3",
        "Hit frame": "KND",
        "Counter hit frame": "KND",
        "Notes": "-"
    },
    {
        "Command": "SBT 3",
        "Hit level": "l",
        "Damage": "17",
        "Start up frame": "16~20s (41~) js1~cs9~",
        "Block frame": "-14~-10",
        "Hit frame": "+4~+8s",
        "Counter hit frame": "KND",
        "Notes": "-"
    },
    {
        "Command": "SBT 4",
        "Hit level": "m",
        "Damage": "22(,5)",
        "Start up frame": "18~19 (43~) js1~",
        "Block frame": "-27~-26",
        "Hit frame": "Launch",
        "Counter hit frame": "Launch",
        "Notes": "-"
    },
    {
        "Command": "d+1+2 or From special move (to DES)",
        "Hit level": "(DES)",
        "Damage": "-",
        "Start up frame": "18~19 (43~) 1~",
        "Block frame": "-",
        "Hit frame": "-",
        "Counter hit frame": "-",
        "Notes": "-"
    },
    {
        "Command": "DES b or F",
        "Hit level": "(DES)",
        "Damage": "-",
        "Start up frame": "18~19 (43~) 1~",
        "Block frame": "-",
        "Hit frame": "-",
        "Counter hit frame": "-",
        "Notes": "-"
    },
    {
        "Command": "DES d+1+2 or D/B (Cancel)",
        "Hit level": "(DES)",
        "Damage": "-",
        "Start up frame": "18~19 (43~) 1~",
        "Block frame": "-",
        "Hit frame": "-",
        "Counter hit frame": "-",
        "Notes": "-"
    },
    {
        "Command": "DES 1",
        "Hit level": "mmhhhm",
        "Damage": "3*5,20",
        "Start up frame": "14,,,",
        "Block frame": "-9",
        "Hit frame": "KZUD",
        "Counter hit frame": "KZUD",
        "Notes": "-"
    },
    {
        "Command": "DES 2",
        "Hit level": "mmm",
        "Damage": "5*3",
        "Start up frame": "20,,",
        "Block frame": "-8",
        "Hit frame": "Launch (JG?)",
        "Counter hit frame": "Launch (JG?)",
        "Notes": "-"
    },
    {
        "Command": "DES 2 When hit 1",
        "Hit level": "m x 3, h!",
        "Damage": "5*3,14",
        "Start up frame": "20,,",
        "Block frame": "-",
        "Hit frame": "Launch",
        "Counter hit frame": "-",
        "Notes": "-"
    },
    {
        "Command": "DES 3 or 4",
        "Hit level": "-",
        "Damage": "-",
        "Start up frame": "20,,",
        "Block frame": "-",
        "Hit frame": "-",
        "Counter hit frame": "-",
        "Notes": "-"
    },
    {
        "Command": "DES 1+2",
        "Hit level": "hhh",
        "Damage": "7,7,20",
        "Start up frame": "16,,",
        "Block frame": "0",
        "Hit frame": "+15k",
        "Counter hit frame": "+15k",
        "Notes": "Homing"
    },
    {
        "Command": "DES f+1",
        "Hit level": "h x 7",
        "Damage": "3*7",
        "Start up frame": "12,,,",
        "Block frame": "+2",
        "Hit frame": "+11",
        "Counter hit frame": "+11",
        "Notes": "-"
    },
    {
        "Command": "DES f+2",
        "Hit level": " (Sky)!",
        "Damage": "3,2,1,1,1",
        "Start up frame": "10,,,",
        "Block frame": "-",
        "Hit frame": "KND",
        "Counter hit frame": "KND",
        "Notes": "-"
    },
    {
        "Command": "DES f+1+2",
        "Hit level": "m x 8",
        "Damage": "3*7,13",
        "Start up frame": "23,,,",
        "Block frame": "+7",
        "Hit frame": "CS",
        "Counter hit frame": "CS",
        "Notes": "-"
    },
    {
        "Command": "DES f+1+2, 1+2",
        "Hit level": "m x 5, m",
        "Damage": "3*5,20(,3)",
        "Start up frame": "23,,,(b)",
        "Block frame": "-53",
        "Hit frame": "Launch",
        "Counter hit frame": "Launch",
        "Notes": "-"
    },
    {
        "Command": "DES d+1",
        "Hit level": "l x 5 (TC)",
        "Damage": "4*4,8",
        "Start up frame": "20~21, cs4~",
        "Block frame": "-12",
        "Hit frame": "+3s",
        "Counter hit frame": "+3s",
        "Notes": "-"
    },
    {
        "Command": "DES d+2",
        "Hit level": "llll",
        "Damage": "5*4",
        "Start up frame": "26,,,",
        "Block frame": "-14~-13",
        "Hit frame": "+2~+3",
        "Counter hit frame": "2~+3",
        "Notes": "-"
    },
    {
        "Command": "DES d+2, *",
        "Hit level": "l x 5 or 6",
        "Damage": "5*5or6",
        "Start up frame": "26,,,",
        "Block frame": "-12~-11",
        "Hit frame": "+4~+5",
        "Counter hit frame": "+4~+5",
        "Notes": "-"
    },
    {
        "Command": "DES b+2",
        "Hit level": "m",
        "Damage": "17",
        "Start up frame": "18~20",
        "Block frame": "-12~-10",
        "Hit frame": "0~+2",
        "Counter hit frame": "CS",
        "Notes": "-"
    },
    {
        "Command": "DES b+2, 1",
        "Hit level": "m, m, Sm x 4",
        "Damage": "17,8,5*4",
        "Start up frame": "18~20",
        "Block frame": "-8s",
        "Hit frame": "KND",
        "Counter hit frame": "KND",
        "Notes": "-"
    },
    {
        "Command": "DES b+3+4 or b, b or u/b, b",
        "Hit level": "(Special) (TJ)",
        "Damage": "-",
        "Start up frame": "a",
        "Block frame": "-",
        "Hit frame": "-",
        "Counter hit frame": "-",
        "Notes": "-"
    },
    {
        "Command": "DES u or d+3+4",
        "Hit level": "(Special) (TJ)",
        "Damage": "-",
        "Start up frame": "-",
        "Block frame": "-",
        "Hit frame": "-",
        "Counter hit frame": "-",
        "Notes": "-"
    },
    {
        "Command": "DES u or d+3+4, 1",
        "Hit level": "(Special) (TJ), m",
        "Damage": "25",
        "Start up frame": "20~21 (44~)",
        "Block frame": "-13",
        "Hit frame": "KND",
        "Counter hit frame": "KND",
        "Notes": "Wall bounce"
    },
    {
        "Command": "DES d/f+1+2",
        "Hit level": "m, (DES)",
        "Damage": "25",
        "Start up frame": "18",
        "Block frame": "-13",
        "Hit frame": "+8k",
        "Counter hit frame": "+8k",
        "Notes": "Power Crush"
    },
    {
        "Command": "DES u/b or u or u/f+1+2",
        "Hit level": "mmm (TJ)",
        "Damage": "9*3",
        "Start up frame": "29,,, js5~28",
        "Block frame": "-9s",
        "Hit frame": "CS",
        "Counter hit frame": "CS",
        "Notes": "-"
    },
    {
        "Command": "DES u/f+1+2, 1+2",
        "Hit level": "m x 3 (TJ), (Special)",
        "Damage": "9*3",
        "Start up frame": "29,,, js5~28",
        "Block frame": "-9s",
        "Hit frame": "CS",
        "Counter hit frame": "CS",
        "Notes": "-"
    },
    {
        "Command": "DES BT 1 or 2",
        "Hit level": "m x 6",
        "Damage": "4*6",
        "Start up frame": "19,,,",
        "Block frame": "-9",
        "Hit frame": "CS",
        "Counter hit frame": "CS",
        "Notes": "-"
    },
    {
        "Command": "DES f+3+4 or f, f (to DBT)",
        "Hit level": "(DBT)",
        "Damage": "-",
        "Start up frame": "19,,,",
        "Block frame": "-",
        "Hit frame": "-",
        "Counter hit frame": "-",
        "Notes": "-"
    },
    {
        "Command": "DBT b (Cancel)",
        "Hit level": "(Special)",
        "Damage": "-",
        "Start up frame": "19,,,",
        "Block frame": "-",
        "Hit frame": "-",
        "Counter hit frame": "-",
        "Notes": "-"
    },
    {
        "Command": "DBT f+3+4, u or D",
        "Hit level": "(Special) (TJ)",
        "Damage": "-",
        "Start up frame": "19,,,",
        "Block frame": "-",
        "Hit frame": "-",
        "Counter hit frame": "-",
        "Notes": "-"
    },
    {
        "Command": "DBT 1",
        "Hit level": "h x 6",
        "Damage": "5*6",
        "Start up frame": "24,,, js1~20",
        "Block frame": "+9",
        "Hit frame": "+11",
        "Counter hit frame": "+11",
        "Notes": "-"
    },
    {
        "Command": "DBT 2",
        "Hit level": "mmhhh",
        "Damage": "8,8,8,20,25",
        "Start up frame": "16~17,,, js1~",
        "Block frame": "-14",
        "Hit frame": "KND",
        "Counter hit frame": "KND",
        "Notes": "-"
    },
    {
        "Command": "DBT 2, 1+2",
        "Hit level": "mmhhh, (Special)",
        "Damage": "8,8,8,20,25",
        "Start up frame": "16~17,,, js1~",
        "Block frame": "-14",
        "Hit frame": "KND",
        "Counter hit frame": "KND",
        "Notes": "-"
    },
    {
        "Command": "DBT 2, 1",
        "Hit level": "mmhh, h (TJ)",
        "Damage": "8,8,8,20,45",
        "Start up frame": "js1~",
        "Block frame": "-12~10s",
        "Hit frame": "KND",
        "Counter hit frame": "KND",
        "Notes": "-"
    },
    {
        "Command": "DBT 2, 1, 1+2",
        "Hit level": "mmhh, h (TJ), (Special)",
        "Damage": "8,8,8,20,45",
        "Start up frame": "js1~",
        "Block frame": "-12~10s",
        "Hit frame": "KND",
        "Counter hit frame": "KND",
        "Notes": "-"
    },
    {
        "Command": "DBT 1+2",
        "Hit level": "mmmm",
        "Damage": "5,5,5,20",
        "Start up frame": "12,,, js1~",
        "Block frame": "0",
        "Hit frame": "KND",
        "Counter hit frame": "KND",
        "Notes": "-"
    },
    {
        "Command": "1",
        "Hit level": "h",
        "Damage": "7",
        "Start up frame": "10",
        "Block frame": "+1",
        "Hit frame": "+8",
        "Counter hit frame": "+8",
        "Notes": "-"
    },
    {
        "Command": "2",
        "Hit level": "h",
        "Damage": "10",
        "Start up frame": "12",
        "Block frame": "-6",
        "Hit frame": "+5",
        "Counter hit frame": "+5",
        "Notes": "-"
    },
    {
        "Command": "3",
        "Hit level": "m",
        "Damage": "12",
        "Start up frame": "14~15",
        "Block frame": "-12~-11",
        "Hit frame": "-1~0",
        "Counter hit frame": "-1~0",
        "Notes": "-"
    },
    {
        "Command": "4",
        "Hit level": "h",
        "Damage": "24",
        "Start up frame": "13~14",
        "Block frame": "-5~-4",
        "Hit frame": "KND",
        "Counter hit frame": "KND",
        "Notes": "Tail spin, Homing"
    },
    {
        "Command": "f+1",
        "Hit level": "h",
        "Damage": "7",
        "Start up frame": "10",
        "Block frame": "+1",
        "Hit frame": "+8",
        "Counter hit frame": "+8",
        "Notes": "-"
    },
    {
        "Command": "f+2",
        "Hit level": "m",
        "Damage": "12",
        "Start up frame": "17~18",
        "Block frame": "-4~-3",
        "Hit frame": "+7~+8",
        "Counter hit frame": "+7~+8",
        "Notes": "-"
    },
    {
        "Command": "f+3",
        "Hit level": "h",
        "Damage": "13",
        "Start up frame": "14~15",
        "Block frame": "-14~-13",
        "Hit frame": "-3~-2",
        "Counter hit frame": "-3~-2",
        "Notes": "-"
    },
    {
        "Command": "f+4",
        "Hit level": "m",
        "Damage": "14",
        "Start up frame": "16",
        "Block frame": "-12",
        "Hit frame": "-2",
        "Counter hit frame": "-2",
        "Notes": "Homing"
    },
    {
        "Command": "d/f+1",
        "Hit level": "m",
        "Damage": "10",
        "Start up frame": "13",
        "Block frame": "-6",
        "Hit frame": "+5",
        "Counter hit frame": "+8",
        "Notes": "-"
    },
    {
        "Command": "d/f+2",
        "Hit level": "m",
        "Damage": "16",
        "Start up frame": "16~17",
        "Block frame": "-9~-8",
        "Hit frame": "Launch (JG?)(+7)",
        "Counter hit frame": "Launch (JG?)",
        "Notes": "-"
    },
    {
        "Command": "d/f+3",
        "Hit level": "m",
        "Damage": "14",
        "Start up frame": "16",
        "Block frame": "-9",
        "Hit frame": "+1",
        "Counter hit frame": "+1",
        "Notes": "-"
    },
    {
        "Command": "d/f+4",
        "Hit level": "m",
        "Damage": "13",
        "Start up frame": "12",
        "Block frame": "-7",
        "Hit frame": "+4",
        "Counter hit frame": "+4",
        "Notes": "-"
    },
    {
        "Command": "d+1",
        "Hit level": "Sm (TC)",
        "Damage": "5",
        "Start up frame": "10s cs4~",
        "Block frame": "-5",
        "Hit frame": "+6",
        "Counter hit frame": "+6",
        "Notes": "-"
    },
    {
        "Command": "d+2",
        "Hit level": "m",
        "Damage": "17",
        "Start up frame": "24~26",
        "Block frame": "-14~-12",
        "Hit frame": "+2~+4s",
        "Counter hit frame": "+2~+4s",
        "Notes": "-"
    },
    {
        "Command": "d+3",
        "Hit level": "l (TJ), (Special) (TC)",
        "Damage": "17",
        "Start up frame": "23~32s js9~",
        "Block frame": "-10~-1",
        "Hit frame": "+8~+17",
        "Counter hit frame": "KND",
        "Notes": "-"
    },
    {
        "Command": "d+4",
        "Hit level": "l",
        "Damage": "15",
        "Start up frame": "17~18",
        "Block frame": "-16~-15",
        "Hit frame": "-5~-4",
        "Counter hit frame": "-5~-4",
        "Notes": "-"
    },
    {
        "Command": "d/b+1",
        "Hit level": "(Special) (TC)",
        "Damage": "-",
        "Start up frame": "s(cs4~) 15~",
        "Block frame": "-",
        "Hit frame": "-",
        "Counter hit frame": "-",
        "Notes": "-"
    },
    {
        "Command": "d/b+2",
        "Hit level": "m",
        "Damage": "17",
        "Start up frame": "18~19",
        "Block frame": "-18~-17",
        "Hit frame": "-5~-4",
        "Counter hit frame": "-5~-4",
        "Notes": "-"
    },
    {
        "Command": "d/b+3",
        "Hit level": "l (TC)",
        "Damage": "11",
        "Start up frame": "16s cs4~",
        "Block frame": "-12",
        "Hit frame": "-1",
        "Counter hit frame": "+4",
        "Notes": "-"
    },
    {
        "Command": "d/b+4",
        "Hit level": "l (TC)",
        "Damage": "23",
        "Start up frame": "24~25a cs6~",
        "Block frame": "-17~-16",
        "Hit frame": "KND",
        "Counter hit frame": "KND",
        "Notes": "-"
    },
    {
        "Command": "b+1",
        "Hit level": "m",
        "Damage": "15",
        "Start up frame": "15~16s",
        "Block frame": "-5~-4",
        "Hit frame": "+8~+9",
        "Counter hit frame": "+8~+9",
        "Notes": "-"
    },
    {
        "Command": "b+2",
        "Hit level": "m",
        "Damage": "12",
        "Start up frame": "18",
        "Block frame": "-12",
        "Hit frame": "-2",
        "Counter hit frame": "-2",
        "Notes": "-"
    },
    {
        "Command": "b+3",
        "Hit level": "m",
        "Damage": "26",
        "Start up frame": "20~22",
        "Block frame": "-8~-6",
        "Hit frame": "ED",
        "Counter hit frame": "ED",
        "Notes": "Homing"
    },
    {
        "Command": "b+4",
        "Hit level": "m",
        "Damage": "17",
        "Start up frame": "15~16",
        "Block frame": "-13~-12",
        "Hit frame": "-4~-3",
        "Counter hit frame": "CS",
        "Notes": "-"
    },
    {
        "Command": "u/b or u or u/f+1",
        "Hit level": "m (TJ)",
        "Damage": "12",
        "Start up frame": "18 js9~",
        "Block frame": "-8",
        "Hit frame": "+3",
        "Counter hit frame": "+3",
        "Notes": "-"
    },
    {
        "Command": "u/b or u or u/f+2",
        "Hit level": "h",
        "Damage": "17",
        "Start up frame": "15~16",
        "Block frame": "-12~-11",
        "Hit frame": "+9~+10g",
        "Counter hit frame": "+9~+10g",
        "Notes": "-"
    },
    {
        "Command": "u/b or u or u/f+3",
        "Hit level": "m (TJ)",
        "Damage": "15",
        "Start up frame": "20~21 js9~",
        "Block frame": "-57~-56",
        "Hit frame": "-29~-28 (SH)",
        "Counter hit frame": "-29~-28 (SH)",
        "Notes": "-"
    },
    {
        "Command": "u/b+4",
        "Hit level": "m (TJ)",
        "Damage": "10",
        "Start up frame": "17~18 js9~",
        "Block frame": "-9~-8",
        "Hit frame": "+7~+8",
        "Counter hit frame": "+7~+8",
        "Notes": "-"
    },
    {
        "Command": "u or u/f+4",
        "Hit level": "m (TJ)",
        "Damage": "10",
        "Start up frame": "15~16 js9~",
        "Block frame": "-15~-14",
        "Hit frame": "-4~-3",
        "Counter hit frame": "-4~-3",
        "Notes": "-"
    },
    {
        "Command": "WS+1",
        "Hit level": "m",
        "Damage": "12",
        "Start up frame": "13~14",
        "Block frame": "-12~-11",
        "Hit frame": "-1~0",
        "Counter hit frame": "-1~0",
        "Notes": "-"
    },
    {
        "Command": "WS+2",
        "Hit level": "m",
        "Damage": "24",
        "Start up frame": "17~18",
        "Block frame": "-13~-12",
        "Hit frame": "Launch",
        "Counter hit frame": "Launch",
        "Notes": "-"
    },
    {
        "Command": "WS+3",
        "Hit level": "m, (Special)",
        "Damage": "18",
        "Start up frame": "19~20a",
        "Block frame": "-137~-136",
        "Hit frame": "-126~-125",
        "Counter hit frame": "-126~-125",
        "Notes": "-"
    },
    {
        "Command": "WS+4",
        "Hit level": "m",
        "Damage": "15",
        "Start up frame": "11~12",
        "Block frame": "-5~-4",
        "Hit frame": "+6~+7",
        "Counter hit frame": "+6~+7",
        "Notes": "-"
    },
    {
        "Command": "FC+1",
        "Hit level": "Sm (TC)",
        "Damage": "5",
        "Start up frame": "10s cs1~",
        "Block frame": "-5",
        "Hit frame": "+6",
        "Counter hit frame": "+6",
        "Notes": "-"
    },
    {
        "Command": "FC+2",
        "Hit level": "Sm (TC)",
        "Damage": "8",
        "Start up frame": "11s cs1~",
        "Block frame": "-4",
        "Hit frame": "+7",
        "Counter hit frame": "+7",
        "Notes": "-"
    },
    {
        "Command": "FC+3",
        "Hit level": "l (TC)",
        "Damage": "12",
        "Start up frame": "16s cs1~",
        "Block frame": "-17",
        "Hit frame": "-3",
        "Counter hit frame": "-3",
        "Notes": "-"
    },
    {
        "Command": "FC+4",
        "Hit level": "l (TC)",
        "Damage": "10",
        "Start up frame": "12s cs1~",
        "Block frame": "-15",
        "Hit frame": "-4",
        "Counter hit frame": "-4",
        "Notes": "-"
    },
    {
        "Command": "SS+1",
        "Hit level": "h",
        "Damage": "7",
        "Start up frame": "10(11~)",
        "Block frame": "+1",
        "Hit frame": "+8",
        "Counter hit frame": "+8",
        "Notes": "-"
    },
    {
        "Command": "SS+2",
        "Hit level": "h",
        "Damage": "10",
        "Start up frame": "12(13~)",
        "Block frame": "-6",
        "Hit frame": "+5",
        "Counter hit frame": "+5",
        "Notes": "-"
    },
    {
        "Command": "SS+3",
        "Hit level": "m",
        "Damage": "12",
        "Start up frame": "14~15 (15~)",
        "Block frame": "-12~-11",
        "Hit frame": "-1~0",
        "Counter hit frame": "-1~0",
        "Notes": "-"
    },
    {
        "Command": "SS+4",
        "Hit level": "l",
        "Damage": "15",
        "Start up frame": "24~25 (33~) cs6~",
        "Block frame": "-12~-11",
        "Hit frame": "-1~0",
        "Counter hit frame": "+7~+8",
        "Notes": "-"
    },
    {
        "Command": "BT 1 or 2",
        "Hit level": "h",
        "Damage": "15",
        "Start up frame": "8",
        "Block frame": "-8",
        "Hit frame": "+3",
        "Counter hit frame": "+3",
        "Notes": "-"
    },
    {
        "Command": "BT 3",
        "Hit level": "h",
        "Damage": "25",
        "Start up frame": "10",
        "Block frame": "-8",
        "Hit frame": "KND",
        "Counter hit frame": "KND",
        "Notes": "-"
    },
    {
        "Command": "BT 4",
        "Hit level": "m (TJ)",
        "Damage": "20",
        "Start up frame": "16~17b",
        "Block frame": "-3~-2",
        "Hit frame": "KND",
        "Counter hit frame": "KND",
        "Notes": "-"
    },
    {
        "Command": "BT d+1 or 2",
        "Hit level": "Sm",
        "Damage": "10",
        "Start up frame": "10s cs1~",
        "Block frame": "-2",
        "Hit frame": "+9",
        "Counter hit frame": "+9",
        "Notes": "-"
    },
    {
        "Command": "BT d+3 or 4",
        "Hit level": "l",
        "Damage": "12",
        "Start up frame": "10s cs1~",
        "Block frame": "-11",
        "Hit frame": "+3",
        "Counter hit frame": "+3",
        "Notes": "-"
    }
]